dev_markdown_flow-0.2.0.dist-info/licenses/LICENSE
markdown_flow/__init__.py
markdown_flow/constants.py
markdown_flow/core.py
markdown_flow/enums.py
markdown_flow/exceptions.py
markdown_flow/llm.py
markdown_flow/models.py
markdown_flow/utils.py
dev_markdown_flow-0.2.0.dist-info/METADATA
dev_markdown_flow-0.2.0.dist-info/WHEEL
dev_markdown_flow-0.2.0.dist-info/top_level.txt
dev_markdown_flow-0.2.0.dist-info/RECORD
