Metadata-Version: 2.4
Name: dev-markdown-flow
Version: 0.2.0
Summary: An agent library designed to parse and process MarkdownFlow documents
Project-URL: Homepage, https://github.com/ai-shifu/markdown-flow-agent-py
Project-URL: Bug Tracker, https://github.com/ai-shifu/markdown-flow-agent-py/issues
Classifier: Development Status :: 3 - Alpha
Classifier: Intended Audience :: Developers
Classifier: License :: OSI Approved :: MIT License
Classifier: Programming Language :: Python :: 3
Classifier: Programming Language :: Python :: 3.10
Classifier: Programming Language :: Python :: 3.11
Classifier: Programming Language :: Python :: 3.12
Requires-Python: >=3.10
License-File: LICENSE
Provides-Extra: dev
Requires-Dist: commitizen>=3.0.0; extra == "dev"
Requires-Dist: pytest>=6.0; extra == "dev"
Requires-Dist: black; extra == "dev"
Requires-Dist: flake8; extra == "dev"
Requires-Dist: mypy; extra == "dev"
Dynamic: license-file
